py_parkour/__init__.py
py_parkour/core/__init__.py
py_parkour/core/context_pool.py
py_parkour/core/driver.py
py_parkour/core/fingerprint.py
py_parkour/core/session.py
py_parkour/core/stealth.py
py_parkour/gadgets/chaos_typer.py
py_parkour/gadgets/compass.py
py_parkour/gadgets/crusher.py
py_parkour/gadgets/disguises.py
py_parkour/gadgets/ghost_cursor.py
py_parkour/gadgets/radar.py
py_parkour/gadgets/shadow.py
py_parkour/gadgets/solicitor.py
py_parkour/gadgets/spatial.py
py_parkour/gadgets/turnstile_solver.py
py_parkour-3.1.0.dist-info/METADATA
py_parkour-3.1.0.dist-info/WHEEL
py_parkour-3.1.0.dist-info/top_level.txt
py_parkour-3.1.0.dist-info/RECORD
