Metadata-Version: 2.4
Name: py-parkour
Version: 3.1.0
Summary: A Hybrid Scraper Framework: cookie consent, auto-pagination, temp identities, session bridging, API discovery, stealth fingerprinting, and Turnstile solving.
Author-email: Zinzied <ziedboughdir@gmail.com>
License: MIT
Project-URL: Homepage, https://github.com/zinzied/Py-Parkour
Project-URL: Repository, https://github.com/zinzied/Py-Parkour
Project-URL: Bug Tracker, https://github.com/zinzied/Py-Parkour/issues
Project-URL: Author, https://github.com/zinzied
Keywords: scraping,automation,playwright,web-scraping,bot,cookies,pagination,api-discovery,fingerprint,stealth,turnstile,cloudscraper
Classifier: Development Status :: 4 - Beta
Classifier: Intended Audience :: Developers
Classifier: License :: OSI Approved :: MIT License
Classifier: Programming Language :: Python :: 3
Classifier: Programming Language :: Python :: 3.8
Classifier: Programming Language :: Python :: 3.9
Classifier: Programming Language :: Python :: 3.10
Classifier: Programming Language :: Python :: 3.11
Classifier: Programming Language :: Python :: 3.12
Classifier: Topic :: Internet :: WWW/HTTP :: Browsers
Classifier: Topic :: Software Development :: Libraries :: Python Modules
Requires-Python: >=3.8
Requires-Dist: aiohttp>=3.8.0
Requires-Dist: beautifulsoup4>=4.11.0
Provides-Extra: full
Requires-Dist: playwright>=1.30.0; extra == "full"
